deepoffense/__init__.py
deepoffense/classification/__init__.py
deepoffense/classification/classification_model.py
deepoffense/classification/classification_utils.py
deepoffense/classification/multi_label_classification_model.py
deepoffense/classification/transformer_models/__init__.py
deepoffense/classification/transformer_models/albert_model.py
deepoffense/classification/transformer_models/bert_model.py
deepoffense/classification/transformer_models/camembert_model.py
deepoffense/classification/transformer_models/distilbert_model.py
deepoffense/classification/transformer_models/flaubert_model.py
deepoffense/classification/transformer_models/mmbt_model.py
deepoffense/classification/transformer_models/roberta_model.py
deepoffense/classification/transformer_models/xlm_model.py
deepoffense/classification/transformer_models/xlm_roberta_model.py
deepoffense/classification/transformer_models/xlnet_model.py
deepoffense/classification/transformer_models/args/__init__.py
deepoffense/classification/transformer_models/args/model_args.py
deepoffense/custom_models/__init__.py
deepoffense/custom_models/models.py
deepoffense/language_modeling/__init__.py
deepoffense/language_modeling/language_modeling_model.py
deepoffense/language_modeling/language_modeling_utils.py
examples/arabic/__init__.py
examples/arabic/arabic_deepoffense.py
examples/arabic/arabic_deepoffense_config.py
examples/bengali/__init__.py
examples/bengali/bengali_deepoffense.py
examples/bengali/bengali_deepoffense_config.py
examples/common/__init__.py
examples/common/download.py
examples/common/evaluation.py
examples/common/label_converter.py
examples/common/print_stat.py
examples/danish/__init__.py
examples/danish/danish_deepoffense.py
examples/danish/danish_deepoffense_config.py
examples/english/__init__.py
examples/english/english_deepoffense.py
examples/english/english_deepoffense_config.py
examples/german/__init__.py
examples/german/german_deepoffense.py
examples/german/german_deepoffense_config.py
deepoffense-0.0.2.dist-info/LICENSE
deepoffense-0.0.2.dist-info/METADATA
deepoffense-0.0.2.dist-info/WHEEL
deepoffense-0.0.2.dist-info/top_level.txt
deepoffense-0.0.2.dist-info/RECORD
